example/scoreboard.v
/*
 * Author:          Cynthia Wang
 * Last modified:   11/11/2023
 * Organization:    ECE 4122
 *
 * Description:
 * A toy Verilog scoreboard that keeps track of PC, opcode, completed for
 * instructions.
*/

`timescale 1ns / 1ps

// Top module 
module scoreboard #(
    parameter SCRBRD_SIZE = 32,
    parameter PC_WIDTH = 32,
    parameter OPCODE_WIDTH = 7
) (
    input       clk,  // Clock
    input       rst,  // Reset 

    // Input data signals
    input [$clog2(SCRBRD_SIZE)-1:0] in_idx,

    input                      in_pc_vld,   
    input [PC_WIDTH-1:0]       in_pc,

    input                      in_opcode_vld,   
    input [OPCODE_WIDTH-1:0]   in_opcode,

    input                      in_completed_vld,   

    input                      in_invalidate_vld
    // Output signals (none)
);    
    /* verilator lint_off UNUSEDSIGNAL */
    reg  [SCRBRD_SIZE-1:0] scrbrd_vld;
    reg  [SCRBRD_SIZE-1:0] scrbrd_completed;

    reg  [PC_WIDTH-1:0]     scrbrd_pc [SCRBRD_SIZE-1:0];
    reg  [OPCODE_WIDTH-1:0] scrbrd_opcode [SCRBRD_SIZE-1:0];

    always @(posedge clk) begin
        if (rst) begin
            scrbrd_vld         <= 'b0;
        end 
        else begin
            if (in_invalidate_vld) begin 
                scrbrd_vld[in_idx] <= 1'b0;
            end
            if (in_completed_vld) begin 
                scrbrd_completed[in_idx] <= 1'b1;
            end
            if (in_pc_vld) begin 
                scrbrd_pc[in_idx] <= in_pc;
                scrbrd_vld[in_idx] <= 1'b1;
            end
            if (in_opcode_vld) begin 
                scrbrd_opcode[in_idx] <= in_opcode;
            end
        end
    end

endmodule: scoreboard

example/waveform.vcd
$version Generated by VerilatedVcd $end
$timescale 1ps $end

 $scope module TOP $end
  $var wire  1 e clk $end
  $var wire  1 l in_completed_vld $end
  $var wire  5 g in_idx [4:0] $end
  $var wire  1 m in_invalidate_vld $end
  $var wire  7 k in_opcode [6:0] $end
  $var wire  1 j in_opcode_vld $end
  $var wire 32 i in_pc [31:0] $end
  $var wire  1 h in_pc_vld $end
  $var wire  1 f rst $end
  $scope module scoreboard $end
   $var wire 32 o OPCODE_WIDTH [31:0] $end
   $var wire 32 n PC_WIDTH [31:0] $end
   $var wire 32 n SCRBRD_SIZE [31:0] $end
   $var wire  1 e clk $end
   $var wire  1 l in_completed_vld $end
   $var wire  5 g in_idx [4:0] $end
   $var wire  1 m in_invalidate_vld $end
   $var wire  7 k in_opcode [6:0] $end
   $var wire  1 j in_opcode_vld $end
   $var wire 32 i in_pc [31:0] $end
   $var wire  1 h in_pc_vld $end
   $var wire  1 f rst $end
   $var wire 32 $ scrbrd_completed [31:0] $end
   $var wire  7 E scrbrd_opcode[0] [6:0] $end
   $var wire  7 O scrbrd_opcode[10] [6:0] $end
   $var wire  7 P scrbrd_opcode[11] [6:0] $end
   $var wire  7 Q scrbrd_opcode[12] [6:0] $end
   $var wire  7 R scrbrd_opcode[13] [6:0] $end
   $var wire  7 S scrbrd_opcode[14] [6:0] $end
   $var wire  7 T scrbrd_opcode[15] [6:0] $end
   $var wire  7 U scrbrd_opcode[16] [6:0] $end
   $var wire  7 V scrbrd_opcode[17] [6:0] $end
   $var wire  7 W scrbrd_opcode[18] [6:0] $end
   $var wire  7 X scrbrd_opcode[19] [6:0] $end
   $var wire  7 F scrbrd_opcode[1] [6:0] $end
   $var wire  7 Y scrbrd_opcode[20] [6:0] $end
   $var wire  7 Z scrbrd_opcode[21] [6:0] $end
   $var wire  7 [ scrbrd_opcode[22] [6:0] $end
   $var wire  7 \ scrbrd_opcode[23] [6:0] $end
   $var wire  7 ] scrbrd_opcode[24] [6:0] $end
   $var wire  7 ^ scrbrd_opcode[25] [6:0] $end
   $var wire  7 _ scrbrd_opcode[26] [6:0] $end
   $var wire  7 ` scrbrd_opcode[27] [6:0] $end
   $var wire  7 a scrbrd_opcode[28] [6:0] $end
   $var wire  7 b scrbrd_opcode[29] [6:0] $end
   $var wire  7 G scrbrd_opcode[2] [6:0] $end
   $var wire  7 c scrbrd_opcode[30] [6:0] $end
   $var wire  7 d scrbrd_opcode[31] [6:0] $end
   $var wire  7 H scrbrd_opcode[3] [6:0] $end
   $var wire  7 I scrbrd_opcode[4] [6:0] $end
   $var wire  7 J scrbrd_opcode[5] [6:0] $end
   $var wire  7 K scrbrd_opcode[6] [6:0] $end
   $var wire  7 L scrbrd_opcode[7] [6:0] $end
   $var wire  7 M scrbrd_opcode[8] [6:0] $end
   $var wire  7 N scrbrd_opcode[9] [6:0] $end
   $var wire 32 % scrbrd_pc[0] [31:0] $end
   $var wire 32 / scrbrd_pc[10] [31:0] $end
   $var wire 32 0 scrbrd_pc[11] [31:0] $end
   $var wire 32 1 scrbrd_pc[12] [31:0] $end
   $var wire 32 2 scrbrd_pc[13] [31:0] $end
   $var wire 32 3 scrbrd_pc[14] [31:0] $end
   $var wire 32 4 scrbrd_pc[15] [31:0] $end
   $var wire 32 5 scrbrd_pc[16] [31:0] $end
   $var wire 32 6 scrbrd_pc[17] [31:0] $end
   $var wire 32 7 scrbrd_pc[18] [31:0] $end
   $var wire 32 8 scrbrd_pc[19] [31:0] $end
   $var wire 32 & scrbrd_pc[1] [31:0] $end
   $var wire 32 9 scrbrd_pc[20] [31:0] $end
   $var wire 32 : scrbrd_pc[21] [31:0] $end
   $var wire 32 ; scrbrd_pc[22] [31:0] $end
   $var wire 32 < scrbrd_pc[23] [31:0] $end
   $var wire 32 = scrbrd_pc[24] [31:0] $end
   $var wire 32 > scrbrd_pc[25] [31:0] $end
   $var wire 32 ? scrbrd_pc[26] [31:0] $end
   $var wire 32 @ scrbrd_pc[27] [31:0] $end
   $var wire 32 A scrbrd_pc[28] [31:0] $end
   $var wire 32 B scrbrd_pc[29] [31:0] $end
   $var wire 32 ' scrbrd_pc[2] [31:0] $end
   $var wire 32 C scrbrd_pc[30] [31:0] $end
   $var wire 32 D scrbrd_pc[31] [31:0] $end
   $var wire 32 ( scrbrd_pc[3] [31:0] $end
   $var wire 32 ) scrbrd_pc[4] [31:0] $end
   $var wire 32 * scrbrd_pc[5] [31:0] $end
   $var wire 32 + scrbrd_pc[6] [31:0] $end
   $var wire 32 , scrbrd_pc[7] [31:0] $end
   $var wire 32 - scrbrd_pc[8] [31:0] $end
   $var wire 32 . scrbrd_pc[9] [31:0] $end
   $var wire 32 # scrbrd_vld [31:0] $end
  $upscope $end
 $upscope $end
$enddefinitions $end


#0
b00000000000000000000000000000000 #
b00000000000000000000000000000000 $
b00000000000000000000000000000000 %
b00000000000000000000000000000000 &
b00000000000000000000000000000000 '
b00000000000000000000000000000000 (
b00000000000000000000000000000000 )
b00000000000000000000000000000000 *
b00000000000000000000000000000000 +
b00000000000000000000000000000000 ,
b00000000000000000000000000000000 -
b00000000000000000000000000000000 .
b00000000000000000000000000000000 /
b00000000000000000000000000000000 0
b00000000000000000000000000000000 1
b00000000000000000000000000000000 2
b00000000000000000000000000000000 3
b00000000000000000000000000000000 4
b00000000000000000000000000000000 5
b00000000000000000000000000000000 6
b00000000000000000000000000000000 7
b00000000000000000000000000000000 8
b00000000000000000000000000000000 9
b00000000000000000000000000000000 :
b00000000000000000000000000000000 ;
b00000000000000000000000000000000 <
b00000000000000000000000000000000 =
b00000000000000000000000000000000 >
b00000000000000000000000000000000 ?
b00000000000000000000000000000000 @
b00000000000000000000000000000000 A
b00000000000000000000000000000000 B
b00000000000000000000000000000000 C
b00000000000000000000000000000000 D
b0000000 E
b0000000 F
b0000000 G
b0000000 H
b0000000 I
b0000000 J
b0000000 K
b0000000 L
b0000000 M
b0000000 N
b0000000 O
b0000000 P
b0000000 Q
b0000000 R
b0000000 S
b0000000 T
b0000000 U
b0000000 V
b0000000 W
b0000000 X
b0000000 Y
b0000000 Z
b0000000 [
b0000000 \
b0000000 ]
b0000000 ^
b0000000 _
b0000000 `
b0000000 a
b0000000 b
b0000000 c
b0000000 d
0e
0f
b00000 g
0h
b00000000000000000000000000000000 i
0j
b0000000 k
0l
0m
b00000000000000000000000000100000 n
b00000000000000000000000000000111 o
#1
1f
#2
1e
#3
0e
0f
#4
1e
#5
b00000000000000000000000000000011 #
b00000000000000101110111011110000 %
b00000000000000101110111011110100 &
b0110011 E
b0110011 F
0e
b00001 g
1h
b00000000000000101110111011110100 i
1j
b0110011 k
#6
1e
#7
b00000000000000000000000000011111 #
b00000000000000101110111011111000 '
b00000000000000101110111011111100 (
b00000000000000101110111100000000 )
b0000011 G
b0000011 H
b0110011 I
0e
b00100 g
b00000000000000101110111100000000 i
#8
1e
#9
b00000000000000000000000001111100 #
b00000000000000000000000000000011 $
b00000000000000101110111100000100 *
b00000000000000101110111100001000 +
b0100011 J
b1100011 K
0e
b00001 g
0h
b00000000000000000000000000000000 i
0j
b0000000 k
1l
1m
#10
1e
#11
0e
b00110 g
1h
b00000000000000101110111100001000 i
1j
b1100011 k
0l
0m
#12
1e
#13
b00000000000000000000011111111100 #
b00000000000000101110111100001100 ,
b00000000000000101110111100010000 -
b00000000000000101110111100010100 .
b00000000000000101110111100011000 /
b0100011 L
b1100011 M
b0100011 N
b1100011 O
0e
b01010 g
b00000000000000101110111100011000 i
#14
1e
#15
b00000000000000000111100001111100 #
b00000000000000000000000001000011 $
b00000000000010111110111011111000 0
b00000000000010111110111011111100 1
b00000000000010111110111100000000 2
b00000000000010111110111100000100 3
b0000011 P
b0000011 Q
b0000011 R
b0000011 S
0e
0h
b00000000000000000000000000000000 i
0j
b0000000 k
1m
#16
1e
#17
b00000000000001111111100001111100 #
b00000000000010111110111100001000 4
b00000000000010111110111100001100 5
b00000000000010111110111100010000 6
b00000000000010111110111100010100 7
b0000011 T
b0000011 U
b0000011 V
b0000011 W
0e
b10010 g
1h
b00000000000010111110111100010100 i
1j
b0000011 k
0m
#18
1e
#19
b00000000000001111111100001110000 #
b00000000000000000111100001001111 $
0e
b01110 g
0h
b00000000000000000000000000000000 i
0j
b0000000 k
1l
#20
1e
#21
b00000000000001111111000000000000 #
b00000000000001111111100001011111 $
0e
b10010 g
#22
1e
#23
b00000000000001110000000000000000 #
0e
b01111 g
0l
1m
#24
1e
#25
b00000000000000000000000000000000 #
0e
b10010 g
